README.md
setup.cfg
setup.py
easy_login/__init__.py
easy_login/python.py
easy_login.egg-info/PKG-INFO
easy_login.egg-info/SOURCES.txt
easy_login.egg-info/dependency_links.txt
easy_login.egg-info/not-zip-safe
easy_login.egg-info/top_level.txt