Metadata-Version: 1.1
Name: easy-login
Version: 3.0.0
Summary: Logging social accounts automatically using python package
Home-page: https://github.com/vasu04gupta/log_in
Author: vasu_gupta
Author-email: UNKNOWN
License: UNKNOWN
Platform: UNKNOWN
Classifier: Programming Language :: Python :: 3
Classifier: Operating System :: OS Independent
